klube/__init__.py
klube/commands/__init__.py
klube/commands/base.py
klube/commands/cp/__init__.py
klube/commands/cp/handler.py
klube/commands/exec/__init__.py
klube/commands/exec/handler.py
klube/commands/klube_config/__init__.py
klube/commands/klube_config/handler.py
klube/commands/logs/__init__.py
klube/commands/logs/handler.py
klube/config.py
klube/main.py
klube-0.1.0.dist-info/METADATA
klube-0.1.0.dist-info/WHEEL
klube-0.1.0.dist-info/RECORD
